rnnr/__init__.py
rnnr/attachments.py
rnnr/callbacks.py
rnnr/event.py
rnnr/py.typed
rnnr/runner.py
rnnr-0.4.0.dist-info/LICENSE
rnnr-0.4.0.dist-info/WHEEL
rnnr-0.4.0.dist-info/METADATA
rnnr-0.4.0.dist-info/RECORD
